HISTORY.rst
MANIFEST.in
README.rst
requirements-test.txt
setup.cfg
setup.py
Flask_Bitmapist.egg-info/PKG-INFO
Flask_Bitmapist.egg-info/SOURCES.txt
Flask_Bitmapist.egg-info/dependency_links.txt
Flask_Bitmapist.egg-info/not-zip-safe
Flask_Bitmapist.egg-info/requires.txt
Flask_Bitmapist.egg-info/top_level.txt
flask_bitmapist/__init__.py
flask_bitmapist/core.py
flask_bitmapist/decorators.py
flask_bitmapist/mixins.py
flask_bitmapist/utils.py
flask_bitmapist/views.py
flask_bitmapist/extensions/__init__.py
flask_bitmapist/extensions/flask_login.py
tests/__init__.py
tests/conftest.py
tests/test_extension.py