Metadata-Version: 1.1
Name: Flask-Bitmapist
Version: 0.1.2
Summary: Flask extension that creates a simple interface to Bitmapist analytics library
Home-page: http://github.com/cuttlesoft/flask-bitmapist
Author: Cuttlesoft, LLC
Author-email: engineering@cuttlesoft.com
License: MIT
Download-URL: https://github.com/cuttlesoft/flask-bitmapist/tarball/0.1.2
Keywords: Flask,Bitmapist
Platform: any
Classifier: Development Status :: 3 - Alpha
Classifier: Environment :: Web Environment
Classifier: Intended Audience :: Developers
Classifier: License :: OSI Approved :: MIT License
Classifier: Operating System :: OS Independent
Classifier: Programming Language :: Python :: 2
Classifier: Topic :: Internet :: WWW/HTTP :: Dynamic Content
Classifier: Topic :: Software Development :: Libraries :: Python Modules
